Workbook

Sheet Пояснения
A1: Параметр | B1: Значение
A2: Вариант | B2: Stepik.org; учебная оценка разработки аналога в оговорённых границах
A3: Авторы | B3: Трикашный Михаил Дмитриевич; Амузинский Артем Андреевич; P3406
A4: Дата | B4: 14.09.2026
A5: Единицы | B5: O/M/P/TE — чел·ч. CPM — рабочие часы при одном исполнителе на работу. Неделя = 40 часов.
A6: Границы | B6: Веб-версия, 24 FR; внешние готовые платёжный, grader, email и media API.
A7: Происхождение оценок | B7: Экспертные учебные допущения, не трудозатраты реальной команды Stepik.
A8: Методы | B8: Наивный = сумма M; PERT = сумма TE; критический путь не является трудоёмкостью.
A9: Ресурсный план | B9: Эвристика приоритета по длине оставшегося пути; 1 исполнитель на задачу, без прерывания.
A10: Рекомендуемая команда | B10: 3
A11: Критерий | B11: Наименьшая из построенных команд 1–8 со сроком не более 110% CPM. Глобальный оптимум не доказывается.
A12: Функциональные точки | B12: DET/RET/FTR — предварительная оценка. EIF=0: внешние API не считаются файлами автоматически.
A13: COCOMO II | B13: Early Design 2000; в SLOC переводится UFP, не AFP. JavaScript: 47 SLOC/FP.
A14: UCP / PF | B14: Завершённого проекта с известными часами у авторов нет. PF=10/20/30 — сценарии, не калибровка.
A15: Пересчёт | B15: При изменении входных данных в data.py запустить build.py; Excel пересчитывает формулы, диаграммы и ресурсный план пересоздаются скриптом.

Sheet Требования
A1: ID | B1: Блок | C1: Функция | D1: Критерий приёмки | E1: Источник / допущение
A2: FR01 | B2: Аккаунт | C2: Регистрация и подтверждение email | D2: Новый адрес создаёт аккаунт; повторный адрес отклоняется; ссылка подтверждает адрес однократно. | E2: S4; П: детали проверки
A3: FR02 | B3: Аккаунт | C3: Вход, выход и восстановление пароля | D3: Верные данные открывают сессию; выход закрывает её; использованный токен сброса повторно не действует. | E3: S4; П: сценарии безопасности
A4: FR03 | B4: Аккаунт | C4: Профиль и настройки уведомлений | D4: Учащийся сохраняет имя и предпочтения; другой пользователь не может их изменить. | E4: S8; П: поля профиля
A5: FR04 | B5: Каталог | C5: Каталог, категории, поиск и фильтры | D5: По запросу и выбранным категории, языку и платности возвращаются подходящие опубликованные курсы. | E5: S1, S2, S10; П: набор фильтров
A6: FR05 | B6: Каталог | C6: Карточка курса | D6: Посетитель видит описание, автора, программу, цену и условия сертификата до записи. | E6: S3, S6, S7; П: состав карточки
A7: FR06 | B7: Обучение | C7: Запись и список моих курсов | D7: Запись на бесплатный курс создаёт один доступ; повторный запрос не дублирует его; курс появляется в кабинете. | E7: S2, S6; П: идемпотентность
A8: FR07 | B8: Обучение | C8: Просмотр текстовых и видеошагов | D8: Зачисленный учащийся открывает доступный шаг, просматривает материал и возвращается к последней позиции. | E8: S3; П: сохранение позиции
A9: FR08 | B9: Обучение | C9: Решение тестовых задач | D9: Выбор варианта, число и строка проверяются по правилам автора; сохраняются ответ и результат попытки. | E9: S5; П: три типа в границах
A10: FR09 | B10: Обучение | C10: Решение задач на программирование | D10: Код отправляется на проверку; учащийся получает статус, итог тестов и диагностическое сообщение; скрытые тесты не раскрываются. | E10: S5; П: интеграция с готовым grader
A11: FR10 | B11: Обучение | C11: Прогресс и баллы | D11: Принятый результат обновляет баллы и долю пройденных шагов; повторный callback не удваивает баллы. | E11: S3, S9; П: правило повторов
A12: FR11 | B12: Обучение | C12: Сертификат | D12: При включённом сертификате и достижении порога формируется документ с именем, курсом, баллами и проверочной ссылкой. | E12: S7; П: формат документа
... A25: FR24 | B25: Администрирование | C25: Управление справочником категорий | D25: Администратор создаёт, переименовывает и архивирует категорию; архивная категория недоступна для нового назначения. | E25: S10; П: административный интерфейс

Sheet Работы
A1: ID | B1: Работа | C1: Результат | D1: FR | E1: Предшественники | F1: O, ч | G1: M, ч | H1: P, ч | I1: TE, ч | J1: σ, ч | K1: Дисперсия, ч²
A2: A01 | B2: Сбор и анализ требований | C2: Границы продукта, роли, критерии приёмки и приоритеты. | D2: все | F2: 24 | G2: 40 | H2: 72 | I2: =(F2+4*G2+H2)/6 -> 42.666667 | J2: =(H2-F2)/6 -> 8 | K2: =J2^2 -> 64
A3: A02 | B3: Архитектура и модель данных | C3: Контракты API, схема БД, границы внешних сервисов, оценка рисков. | D3: все | E3: A01 | F3: 32 | G3: 56 | H3: 96 | I3: =(F3+4*G3+H3)/6 -> 58.666667 | J3: =(H3-F3)/6 -> 10.666667 | K3: =J3^2 -> 113.77778
A4: A03 | B4: Прототипы и дизайн | C4: Экраны учащегося, автора и модератора; состояния ошибок, мобильные макеты. | D4: все | E4: A01 | F4: 48 | G4: 80 | H4: 128 | I4: =(F4+4*G4+H4)/6 -> 82.666667 | J4: =(H4-F4)/6 -> 13.333333 | K4: =J4^2 -> 177.77778
A5: A04 | B5: Каркас приложения и CI | C5: Окружение, миграции, сборка, автоматический запуск проверок. | D5: все | E5: A02 | F5: 32 | G5: 48 | H5: 80 | I5: =(F5+4*G5+H5)/6 -> 50.666667 | J5: =(H5-F5)/6 -> 8 | K5: =J5^2 -> 64
A6: A05 | B6: Аккаунты и роли | C6: Email-регистрация, сессии, восстановление и проверка ролей. | D6: FR01 FR02 FR19 | E6: A04 | F6: 56 | G6: 88 | H6: 144 | I6: =(F6+4*G6+H6)/6 -> 92 | J6: =(H6-F6)/6 -> 14.666667 | K6: =J6^2 -> 215.11111
A7: A06 | B7: Профиль и настройки | C7: Формы профиля и предпочтений уведомлений. | D7: FR03 | E7: A05, A03 | F7: 24 | G7: 40 | H7: 64 | I7: =(F7+4*G7+H7)/6 -> 41.333333 | J7: =(H7-F7)/6 -> 6.6666667 | K7: =J7^2 -> 44.444444
A8: A07 | B8: Редактор курса и категории | C8: Черновик и публикация, категории, описание, управление справочником. | D8: FR15 FR24 | E8: A05, A03 | F8: 64 | G8: 96 | H8: 160 | I8: =(F8+4*G8+H8)/6 -> 101.33333 | J8: =(H8-F8)/6 -> 16 | K8: =J8^2 -> 256
A9: A08 | B9: Редактор структуры и материалов | C9: Модули, уроки, шаги, загрузка медиа через объектное хранилище. | D9: FR16 | E9: A07 | F9: 80 | G9: 120 | H9: 200 | I9: =(F9+4*G9+H9)/6 -> 126.66667 | J9: =(H9-F9)/6 -> 20 | K9: =J9^2 -> 400
A10: A09 | B10: Редактор тестовых заданий | C10: Выбор, число, строка; правила проверки и баллы. | D10: FR17 | E10: A08 | F10: 48 | G10: 80 | H10: 136 | I10: =(F10+4*G10+H10)/6 -> 84 | J10: =(H10-F10)/6 -> 14.666667 | K10: =J10^2 -> 215.11111
A11: A10 | B11: Интеграция проверки кода | C11: API готового изолированного grader, очередь, лимиты, пробный запуск и callback. | D11: FR09 FR17 | E11: A09 | F11: 96 | G11: 160 | H11: 280 | I11: =(F11+4*G11+H11)/6 -> 169.33333 | J11: =(H11-F11)/6 -> 30.666667 | K11: =J11^2 -> 940.44444
A12: A11 | B12: Каталог и поиск | C12: Поиск, фильтры, категории, пагинация. | D12: FR04 | E12: A07, A03 | F12: 56 | G12: 88 | H12: 144 | I12: =(F12+4*G12+H12)/6 -> 92 | J12: =(H12-F12)/6 -> 14.666667 | K12: =J12^2 -> 215.11111
A13: A12 | B13: Карточка курса | C13: Описание, программа, преподаватели, цена, сертификат. | D13: FR05 | E13: A08, A11 | F13: 32 | G13: 48 | H13: 80 | I13: =(F13+4*G13+H13)/6 -> 50.666667 | J13: =(H13-F13)/6 -> 8 | K13: =J13^2 -> 64
A14: A13 | B14: Запись и кабинет учащегося | C14: Запись, список курсов, выдача и отзыв приватного доступа. | D14: FR06 FR19 | E14: A05, A07, A03 | F14: 40 | G14: 64 | H14: 104 | I14: =(F14+4*G14+H14)/6 -> 66.666667 | J14: =(H14-F14)/6 -> 10.666667 | K14: =J14^2 -> 113.77778
... A33: A32 | B33: Приёмка и выпуск | C33: Приёмочные сценарии, развёртывание, smoke-проверка, передача продукта. | D33: все | E33: A30, A31 | F33: 32 | G33: 48 | H33: 88 | I33: =(F33+4*G33+H33)/6 -> 52 | J33: =(H33-F33)/6 -> 9.3333333 | K33: =J33^2 -> 87.111111
A34: ИТОГО | F34: =SUM(F2:F33) -> 1432 | G34: =SUM(G2:G33) -> 2304 | H34: =SUM(H2:H33) -> 3920 | I34: =SUM(I2:I33) -> 2428 | J34: =SQRT(SUM(K2:K33)) -> 78.145164 | K34: =SUM(K2:K33) -> 6106.6667

Sheet CPM
A1: ID | B1: Работа | C1: TE | D1: ES | E1: EF | F1: LS | G1: LF | H1: Резерв | I1: Критическая
A2: A01 | B2: Сбор и анализ требований | C2: =Работы!I2 -> 42.666667 | D2: =0 -> 0 | E2: =D2+C2 -> 42.666667 | F2: =G2-C2 -> 0 | G2: =MIN(F3,F4) -> 42.666667 | H2: =F2-D2 -> 0 | I2: =IF(ABS(H2)<0.000001,1,0) -> 1
A3: A02 | B3: Архитектура и модель данных | C3: =Работы!I3 -> 58.666667 | D3: =MAX(E2) -> 42.666667 | E3: =D3+C3 -> 101.33333 | F3: =G3-C3 -> 42.666667 | G3: =MIN(F5) -> 101.33333 | H3: =F3-D3 -> 0 | I3: =IF(ABS(H3)<0.000001,1,0) -> 1
A4: A03 | B4: Прототипы и дизайн | C4: =Работы!I4 -> 82.666667 | D4: =MAX(E2) -> 42.666667 | E4: =D4+C4 -> 125.33333 | F4: =G4-C4 -> 161.33333 | G4: =MIN(F7,F8,F12,F14) -> 244 | H4: =F4-D4 -> 118.66667 | I4: =IF(ABS(H4)<0.000001,1,0) -> 0
A5: A04 | B5: Каркас приложения и CI | C5: =Работы!I5 -> 50.666667 | D5: =MAX(E3) -> 101.33333 | E5: =D5+C5 -> 152 | F5: =G5-C5 -> 101.33333 | G5: =MIN(F6) -> 152 | H5: =F5-D5 -> 0 | I5: =IF(ABS(H5)<0.000001,1,0) -> 1
A6: A05 | B6: Аккаунты и роли | C6: =Работы!I6 -> 92 | D6: =MAX(E5) -> 152 | E6: =D6+C6 -> 244 | F6: =G6-C6 -> 152 | G6: =MIN(F7,F8,F14) -> 244 | H6: =F6-D6 -> 0 | I6: =IF(ABS(H6)<0.000001,1,0) -> 1
A7: A06 | B7: Профиль и настройки | C7: =Работы!I7 -> 41.333333 | D7: =MAX(E6,E4) -> 244 | E7: =D7+C7 -> 285.33333 | F7: =G7-C7 -> 837.33333 | G7: =MIN(F23) -> 878.66667 | H7: =F7-D7 -> 593.33333 | I7: =IF(ABS(H7)<0.000001,1,0) -> 0
A8: A07 | B8: Редактор курса и категории | C8: =Работы!I8 -> 101.33333 | D8: =MAX(E6,E4) -> 244 | E8: =D8+C8 -> 345.33333 | F8: =G8-C8 -> 244 | G8: =MIN(F9,F12,F14,F23,F27) -> 345.33333 | H8: =F8-D8 -> 0 | I8: =IF(ABS(H8)<0.000001,1,0) -> 1
A9: A08 | B9: Редактор структуры и материалов | C9: =Работы!I9 -> 126.66667 | D9: =MAX(E8) -> 345.33333 | E9: =D9+C9 -> 472 | F9: =G9-C9 -> 345.33333 | G9: =MIN(F10,F13,F15) -> 472 | H9: =F9-D9 -> 0 | I9: =IF(ABS(H9)<0.000001,1,0) -> 1
A10: A09 | B10: Редактор тестовых заданий | C10: =Работы!I10 -> 84 | D10: =MAX(E9) -> 472 | E10: =D10+C10 -> 556 | F10: =G10-C10 -> 472 | G10: =MIN(F11,F16) -> 556 | H10: =F10-D10 -> 0 | I10: =IF(ABS(H10)<0.000001,1,0) -> 1
A11: A10 | B11: Интеграция проверки кода | C11: =Работы!I11 -> 169.33333 | D11: =MAX(E10) -> 556 | E11: =D11+C11 -> 725.33333 | F11: =G11-C11 -> 556 | G11: =MIN(F17,F29) -> 725.33333 | H11: =F11-D11 -> 0 | I11: =IF(ABS(H11)<0.000001,1,0) -> 1
A12: A11 | B12: Каталог и поиск | C12: =Работы!I12 -> 92 | D12: =MAX(E8,E4) -> 345.33333 | E12: =D12+C12 -> 437.33333 | F12: =G12-C12 -> 641.33333 | G12: =MIN(F13) -> 733.33333 | H12: =F12-D12 -> 296 | I12: =IF(ABS(H12)<0.000001,1,0) -> 0
A13: A12 | B13: Карточка курса | C13: =Работы!I13 -> 50.666667 | D13: =MAX(E9,E12) -> 472 | E13: =D13+C13 -> 522.66667 | F13: =G13-C13 -> 733.33333 | G13: =MIN(F22,F24) -> 784 | H13: =F13-D13 -> 261.33333 | I13: =IF(ABS(H13)<0.000001,1,0) -> 0
A14: A13 | B14: Запись и кабинет учащегося | C14: =Работы!I14 -> 66.666667 | D14: =MAX(E6,E8,E4) -> 345.33333 | E14: =D14+C14 -> 412 | F14: =G14-C14 -> 484 | G14: =MIN(F15,F22,F24) -> 550.66667 | H14: =F14-D14 -> 138.66667 | I14: =IF(ABS(H14)<0.000001,1,0) -> 0
A15: A14 | B15: Проигрыватель учебных шагов | C15: =Работы!I15 -> 109.33333 | D15: =MAX(E9,E14) -> 472 | E15: =D15+C15 -> 581.33333 | F15: =G15-C15 -> 550.66667 | G15: =MIN(F16,F17,F21) -> 660 | H15: =F15-D15 -> 78.666667 | I15: =IF(ABS(H15)<0.000001,1,0) -> 0
A16: A15 | B16: Приём и проверка тестовых ответов | C16: =Работы!I16 -> 82.666667 | D16: =MAX(E10,E15) -> 581.33333 | E16: =D16+C16 -> 664 | F16: =G16-C16 -> 660 | G16: =MIN(F18,F19) -> 742.66667 | H16: =F16-D16 -> 78.666667 | I16: =IF(ABS(H16)<0.000001,1,0) -> 0
A17: A16 | B17: Интерфейс решения задач на код | C17: =Работы!I17 -> 85.333333 | D17: =MAX(E11,E15) -> 725.33333 | E17: =D17+C17 -> 810.66667 | F17: =G17-C17 -> 725.33333 | G17: =MIN(F19) -> 810.66667 | H17: =F17-D17 -> 0 | I17: =IF(ABS(H17)<0.000001,1,0) -> 1
A18: A17 | B18: Проверка преподавателем | C18: =Работы!I18 -> 68 | D18: =MAX(E16) -> 664 | E18: =D18+C18 -> 732 | F18: =G18-C18 -> 742.66667 | G18: =MIN(F19) -> 810.66667 | H18: =F18-D18 -> 78.666667 | I18: =IF(ABS(H18)<0.000001,1,0) -> 0
A19: A18 | B19: Прогресс и начисление баллов | C19: =Работы!I19 -> 68 | D19: =MAX(E16,E17,E18) -> 810.66667 | E19: =D19+C19 -> 878.66667 | F19: =G19-C19 -> 810.66667 | G19: =MIN(F20,F26) -> 878.66667 | H19: =F19-D19 -> 0 | I19: =IF(ABS(H19)<0.000001,1,0) -> 1
A20: A19 | B20: Выдача сертификатов | C20: =Работы!I20 -> 58.666667 | D20: =MAX(E19) -> 878.66667 | E20: =D20+C20 -> 937.33333 | F20: =G20-C20 -> 888 | G20: =MIN(F28) -> 946.66667 | H20: =F20-D20 -> 9.3333333 | I20: =IF(ABS(H20)<0.000001,1,0) -> 0
A21: A20 | B21: Комментарии и ответы | C21: =Работы!I21 -> 66.666667 | D21: =MAX(E15) -> 581.33333 | E21: =D21+C21 -> 648 | F21: =G21-C21 -> 796 | G21: =MIN(F27) -> 862.66667 | H21: =F21-D21 -> 214.66667 | I21: =IF(ABS(H21)<0.000001,1,0) -> 0
A22: A21 | B22: Отзывы и рейтинг | C22: =Работы!I22 -> 50.666667 | D22: =MAX(E13,E14) -> 522.66667 | E22: =D22+C22 -> 573.33333 | F22: =G22-C22 -> 812 | G22: =MIN(F27) -> 862.66667 | H22: =F22-D22 -> 289.33333 | I22: =IF(ABS(H22)<0.000001,1,0) -> 0
A23: A22 | B23: Новости и уведомления | C23: =Работы!I23 -> 68 | D23: =MAX(E7,E8) -> 345.33333 | E23: =D23+C23 -> 413.33333 | F23: =G23-C23 -> 878.66667 | G23: =MIN(F28) -> 946.66667 | H23: =F23-D23 -> 533.33333 | I23: =IF(ABS(H23)<0.000001,1,0) -> 0
A24: A23 | B24: Заказы и платежи | C24: =Работы!I24 -> 110.66667 | D24: =MAX(E13,E14) -> 522.66667 | E24: =D24+C24 -> 633.33333 | F24: =G24-C24 -> 784 | G24: =MIN(F25,F29) -> 894.66667 | H24: =F24-D24 -> 261.33333 | I24: =IF(ABS(H24)<0.000001,1,0) -> 0
A25: A24 | B25: Цены и промокоды | C25: =Работы!I25 -> 52 | D25: =MAX(E24) -> 633.33333 | E25: =D25+C25 -> 685.33333 | F25: =G25-C25 -> 894.66667 | G25: =MIN(F28,F32) -> 946.66667 | H25: =F25-D25 -> 261.33333 | I25: =IF(ABS(H25)<0.000001,1,0) -> 0
A26: A25 | B26: Отчёты преподавателя | C26: =Работы!I26 -> 68 | D26: =MAX(E19) -> 878.66667 | E26: =D26+C26 -> 946.66667 | F26: =G26-C26 -> 878.66667 | G26: =MIN(F28,F32) -> 946.66667 | H26: =F26-D26 -> 0 | I26: =IF(ABS(H26)<0.000001,1,0) -> 1
A27: A26 | B27: Модерация и аудит | C27: =Работы!I27 -> 66.666667 | D27: =MAX(E21,E22,E8) -> 648 | E27: =D27+C27 -> 714.66667 | F27: =G27-C27 -> 862.66667 | G27: =MIN(F28,F29,F32) -> 929.33333 | H27: =F27-D27 -> 214.66667 | I27: =IF(ABS(H27)<0.000001,1,0) -> 0
A28: A27 | B28: Проверка адаптивности и доступности | C28: =Работы!I28 -> 58.666667 | D28: =MAX(E20,E23,E25,E26,E27) -> 946.66667 | E28: =D28+C28 -> 1005.3333 | F28: =G28-C28 -> 946.66667 | G28: =MIN(F30) -> 1005.3333 | H28: =F28-D28 -> 0 | I28: =IF(ABS(H28)<0.000001,1,0) -> 1
A29: A28 | B29: Безопасность интеграций | C29: =Работы!I29 -> 76 | D29: =MAX(E11,E24,E27) -> 725.33333 | E29: =D29+C29 -> 801.33333 | F29: =G29-C29 -> 929.33333 | G29: =MIN(F30) -> 1005.3333 | H29: =F29-D29 -> 204 | I29: =IF(ABS(H29)<0.000001,1,0) -> 0
A30: A29 | B30: Интеграционные и сквозные проверки | C30: =Работы!I30 -> 109.33333 | D30: =MAX(E28,E29) -> 1005.3333 | E30: =D30+C30 -> 1114.6667 | F30: =G30-C30 -> 1005.3333 | G30: =MIN(F31) -> 1114.6667 | H30: =F30-D30 -> 0 | I30: =IF(ABS(H30)<0.000001,1,0) -> 1
A31: A30 | B31: Нагрузка и оптимизация | C31: =Работы!I31 -> 68 | D31: =MAX(E30) -> 1114.6667 | E31: =D31+C31 -> 1182.6667 | F31: =G31-C31 -> 1114.6667 | G31: =MIN(F33) -> 1182.6667 | H31: =F31-D31 -> 0 | I31: =IF(ABS(H31)<0.000001,1,0) -> 1
A32: A31 | B32: Документация и эксплуатационные инструкции | C32: =Работы!I32 -> 50.666667 | D32: =MAX(E26,E27,E25) -> 946.66667 | E32: =D32+C32 -> 997.33333 | F32: =G32-C32 -> 1132 | G32: =MIN(F33) -> 1182.6667 | H32: =F32-D32 -> 185.33333 | I32: =IF(ABS(H32)<0.000001,1,0) -> 0
A33: A32 | B33: Приёмка и выпуск | C33: =Работы!I33 -> 52 | D33: =MAX(E31,E32) -> 1182.6667 | E33: =D33+C33 -> 1234.6667 | F33: =G33-C33 -> 1182.6667 | G33: =MAX(E2:E33) -> 1234.6667 | H33: =F33-D33 -> 0 | I33: =IF(ABS(H33)<0.000001,1,0) -> 1

Sheet Команда
A1: Исполнителей | B1: Нижняя граница, ч | C1: Расписание, ч | D1: Рабочих недель | E1: Загрузка | F1: Отклонение от CPM
A2: 1 | B2: 2428 | C2: 2428 | D2: 60.7 | E2: 1 | F2: 0.96652268
A3: 2 | B3: 1234.6667 | C3: 1425.3333 | D3: 35.633333 | E3: 0.85173059 | F3: 0.15442765
A4: 3 | B4: 1234.6667 | C4: 1234.6667 | D4: 30.866667 | E4: 0.65550756 | F4: 0
A5: 4 | B5: 1234.6667 | C5: 1234.6667 | D5: 30.866667 | E5: 0.49163067 | F5: 0
A6: 5 | B6: 1234.6667 | C6: 1234.6667 | D6: 30.866667 | E6: 0.39330454 | F6: 0
A7: 6 | B7: 1234.6667 | C7: 1234.6667 | D7: 30.866667 | E7: 0.32775378 | F7: 0
A8: 7 | B8: 1234.6667 | C8: 1234.6667 | D8: 30.866667 | E8: 0.28093181 | F8: 0
A9: 8 | B9: 1234.6667 | C9: 1234.6667 | D9: 30.866667 | E9: 0.24581533 | F9: 0

Sheet Расписание
A1: ID | B1: Работа | C1: Исполнитель | D1: Старт, ч | E1: Финиш, ч | F1: Старт, неделя | G1: Финиш, неделя
A2: A01 | B2: Сбор и анализ требований | C2: 1 | D2: 0 | E2: 42.666667 | F2: 0 | G2: 1.0666667
A3: A02 | B3: Архитектура и модель данных | C3: 1 | D3: 42.666667 | E3: 101.33333 | F3: 1.0666667 | G3: 2.5333333
A4: A03 | B4: Прототипы и дизайн | C4: 2 | D4: 42.666667 | E4: 125.33333 | F4: 1.0666667 | G4: 3.1333333
A5: A04 | B5: Каркас приложения и CI | C5: 1 | D5: 101.33333 | E5: 152 | F5: 2.5333333 | G5: 3.8
A6: A05 | B6: Аккаунты и роли | C6: 1 | D6: 152 | E6: 244 | F6: 3.8 | G6: 6.1
A7: A06 | B7: Профиль и настройки | C7: 2 | D7: 244 | E7: 285.33333 | F7: 6.1 | G7: 7.1333333
A8: A07 | B8: Редактор курса и категории | C8: 1 | D8: 244 | E8: 345.33333 | F8: 6.1 | G8: 8.6333333
A9: A08 | B9: Редактор структуры и материалов | C9: 1 | D9: 345.33333 | E9: 472 | F9: 8.6333333 | G9: 11.8
A10: A09 | B10: Редактор тестовых заданий | C10: 1 | D10: 472 | E10: 556 | F10: 11.8 | G10: 13.9
A11: A10 | B11: Интеграция проверки кода | C11: 1 | D11: 556 | E11: 725.33333 | F11: 13.9 | G11: 18.133333
A12: A11 | B12: Каталог и поиск | C12: 3 | D12: 345.33333 | E12: 437.33333 | F12: 8.6333333 | G12: 10.933333
A13: A12 | B13: Карточка курса | C13: 2 | D13: 480 | E13: 530.66667 | F13: 12 | G13: 13.266667
... A33: A32 | B33: Приёмка и выпуск | C33: 1 | D33: 1182.6667 | E33: 1234.6667 | F33: 29.566667 | G33: 30.866667

Sheet FP данные
A1: ID | B1: Логическая группа | C1: Тип | D1: RET | E1: DET | F1: Сложность | G1: FP | H1: Состав
A2: D01 | B2: Пользователи | C2: ILF | D2: 2 | E2: 18 | F2: =CHOOSE(IF(D2=1,IF(E2<=50,1,2),IF(D2<=5,IF(E2<=19,1,IF(E2<=50,2,3)),IF(E2<=19,2,3))),"Низкая","Средняя","Высокая") -> Низкая | G2: =CHOOSE(IF(D2=1,IF(E2<=50,1,2),IF(D2<=5,IF(E2<=19,1,IF(E2<=50,2,3)),IF(E2<=19,2,3))),7,10,15) -> 7 | H2: Профиль, настройки и роли: имя, email, статус, предпочтения и др.
A3: D02 | B3: Курсы | C3: ILF | D3: 3 | E3: 32 | F3: =CHOOSE(IF(D3=1,IF(E3<=50,1,2),IF(D3<=5,IF(E3<=19,1,IF(E3<=50,2,3)),IF(E3<=19,2,3))),"Низкая","Средняя","Высокая") -> Средняя | G3: =CHOOSE(IF(D3=1,IF(E3<=50,1,2),IF(D3<=5,IF(E3<=19,1,IF(E3<=50,2,3)),IF(E3<=19,2,3))),7,10,15) -> 10 | H3: Описание, программа верхнего уровня, настройки доступа/сертификата/цены.
A4: D03 | B4: Учебные материалы | C4: ILF | D4: 3 | E4: 28 | F4: =CHOOSE(IF(D4=1,IF(E4<=50,1,2),IF(D4<=5,IF(E4<=19,1,IF(E4<=50,2,3)),IF(E4<=19,2,3))),"Низкая","Средняя","Высокая") -> Средняя | G4: =CHOOSE(IF(D4=1,IF(E4<=50,1,2),IF(D4<=5,IF(E4<=19,1,IF(E4<=50,2,3)),IF(E4<=19,2,3))),7,10,15) -> 10 | H4: Модули, уроки и шаги: порядок, заголовок, тип, текст и ссылка на медиа.
A5: D04 | B5: Задания | C5: ILF | D5: 3 | E5: 24 | F5: =CHOOSE(IF(D5=1,IF(E5<=50,1,2),IF(D5<=5,IF(E5<=19,1,IF(E5<=50,2,3)),IF(E5<=19,2,3))),"Низкая","Средняя","Высокая") -> Средняя | G5: =CHOOSE(IF(D5=1,IF(E5<=50,1,2),IF(D5<=5,IF(E5<=19,1,IF(E5<=50,2,3)),IF(E5<=19,2,3))),7,10,15) -> 10 | H5: Условия, варианты/эталоны и параметры программных тестов.
A6: D05 | B6: Записи на курсы | C6: ILF | D6: 1 | E6: 8 | F6: =CHOOSE(IF(D6=1,IF(E6<=50,1,2),IF(D6<=5,IF(E6<=19,1,IF(E6<=50,2,3)),IF(E6<=19,2,3))),"Низкая","Средняя","Высокая") -> Низкая | G6: =CHOOSE(IF(D6=1,IF(E6<=50,1,2),IF(D6<=5,IF(E6<=19,1,IF(E6<=50,2,3)),IF(E6<=19,2,3))),7,10,15) -> 7 | H6: Учащийся, курс, источник доступа, статус, даты, последняя позиция.
A7: D06 | B7: Попытки и результаты | C7: ILF | D7: 2 | E7: 18 | F7: =CHOOSE(IF(D7=1,IF(E7<=50,1,2),IF(D7<=5,IF(E7<=19,1,IF(E7<=50,2,3)),IF(E7<=19,2,3))),"Низкая","Средняя","Высокая") -> Низкая | G7: =CHOOSE(IF(D7=1,IF(E7<=50,1,2),IF(D7<=5,IF(E7<=19,1,IF(E7<=50,2,3)),IF(E7<=19,2,3))),7,10,15) -> 7 | H7: Ответ, код, статус, обратная связь, баллы; прогресс вычисляется из результатов.
A8: D07 | B8: Обсуждения | C8: ILF | D8: 2 | E8: 12 | F8: =CHOOSE(IF(D8=1,IF(E8<=50,1,2),IF(D8<=5,IF(E8<=19,1,IF(E8<=50,2,3)),IF(E8<=19,2,3))),"Низкая","Средняя","Высокая") -> Низкая | G8: =CHOOSE(IF(D8=1,IF(E8<=50,1,2),IF(D8<=5,IF(E8<=19,1,IF(E8<=50,2,3)),IF(E8<=19,2,3))),7,10,15) -> 7 | H8: Комментарии и ответы: автор, шаг, текст, время, статус.
A9: D08 | B9: Отзывы | C9: ILF | D9: 1 | E9: 8 | F9: =CHOOSE(IF(D9=1,IF(E9<=50,1,2),IF(D9<=5,IF(E9<=19,1,IF(E9<=50,2,3)),IF(E9<=19,2,3))),"Низкая","Средняя","Высокая") -> Низкая | G9: =CHOOSE(IF(D9=1,IF(E9<=50,1,2),IF(D9<=5,IF(E9<=19,1,IF(E9<=50,2,3)),IF(E9<=19,2,3))),7,10,15) -> 7 | H9: Автор, курс, оценка, текст, даты и статус.
A10: D09 | B10: Заказы | C10: ILF | D10: 2 | E10: 18 | F10: =CHOOSE(IF(D10=1,IF(E10<=50,1,2),IF(D10<=5,IF(E10<=19,1,IF(E10<=50,2,3)),IF(E10<=19,2,3))),"Низкая","Средняя","Высокая") -> Низкая | G10: =CHOOSE(IF(D10=1,IF(E10<=50,1,2),IF(D10<=5,IF(E10<=19,1,IF(E10<=50,2,3)),IF(E10<=19,2,3))),7,10,15) -> 7 | H10: Заказ и состояние платежа; курс, покупатель, сумма, ключ провайдера.
A11: D10 | B11: Промокоды | C11: ILF | D11: 1 | E11: 9 | F11: =CHOOSE(IF(D11=1,IF(E11<=50,1,2),IF(D11<=5,IF(E11<=19,1,IF(E11<=50,2,3)),IF(E11<=19,2,3))),"Низкая","Средняя","Высокая") -> Низкая | G11: =CHOOSE(IF(D11=1,IF(E11<=50,1,2),IF(D11<=5,IF(E11<=19,1,IF(E11<=50,2,3)),IF(E11<=19,2,3))),7,10,15) -> 7 | H11: Код, курс, скидка, срок, лимит, счётчик и статус.
A12: D11 | B12: Сертификаты | C12: ILF | D12: 1 | E12: 9 | F12: =CHOOSE(IF(D12=1,IF(E12<=50,1,2),IF(D12<=5,IF(E12<=19,1,IF(E12<=50,2,3)),IF(E12<=19,2,3))),"Низкая","Средняя","Высокая") -> Низкая | G12: =CHOOSE(IF(D12=1,IF(E12<=50,1,2),IF(D12<=5,IF(E12<=19,1,IF(E12<=50,2,3)),IF(E12<=19,2,3))),7,10,15) -> 7 | H12: Идентификатор, учащийся, курс, баллы, вид, дата, ссылка.
A13: D12 | B13: Новости и уведомления | C13: ILF | D13: 2 | E13: 15 | F13: =CHOOSE(IF(D13=1,IF(E13<=50,1,2),IF(D13<=5,IF(E13<=19,1,IF(E13<=50,2,3)),IF(E13<=19,2,3))),"Низкая","Средняя","Высокая") -> Низкая | G13: =CHOOSE(IF(D13=1,IF(E13<=50,1,2),IF(D13<=5,IF(E13<=19,1,IF(E13<=50,2,3)),IF(E13<=19,2,3))),7,10,15) -> 7 | H13: Авторский текст новости и уведомления адресатам, статус прочтения.
... A15: D14 | B15: Журнал модерации | C15: ILF | D15: 1 | E15: 9 | F15: =CHOOSE(IF(D15=1,IF(E15<=50,1,2),IF(D15<=5,IF(E15<=19,1,IF(E15<=50,2,3)),IF(E15<=19,2,3))),"Низкая","Средняя","Высокая") -> Низкая | G15: =CHOOSE(IF(D15=1,IF(E15<=50,1,2),IF(D15<=5,IF(E15<=19,1,IF(E15<=50,2,3)),IF(E15<=19,2,3))),7,10,15) -> 7 | H15: Модератор, объект, действие, причина, время и прежний статус.

Sheet FP транзакции
A1: ID | B1: Процесс | C1: Тип | D1: FTR | E1: DET | F1: Сложность | G1: FP | H1: Группы данных | I1: FR
A2: F01 | B2: Регистрация | C2: EI | D2: 1 | E2: 6 | F2: =CHOOSE(IF(C2="EI",IF(D2<=1,IF(E2<=15,1,2),IF(D2=2,IF(E2<=4,1,IF(E2<=15,2,3)),IF(E2<=4,2,3))),IF(D2<=1,IF(E2<=19,1,2),IF(D2<=3,IF(E2<=5,1,IF(E2<=19,2,3)),IF(E2<=5,2,3)))),"Низкая","Средняя","Высокая") -> Низкая | G2: =IF(C2="EI",CHOOSE(IF(C2="EI",IF(D2<=1,IF(E2<=15,1,2),IF(D2=2,IF(E2<=4,1,IF(E2<=15,2,3)),IF(E2<=4,2,3))),IF(D2<=1,IF(E2<=19,1,2),IF(D2<=3,IF(E2<=5,1,IF(E2<=19,2,3)),IF(E2<=5,2,3)))),3,4,6),IF(C2="EO",CHOOSE(IF(C2="EI",IF(D2<=1,IF(E2<=15,1,2),IF(D2=2,IF(E2<=4,1,IF(E2<=15,2,3)),IF(E2<=4,2,3))),IF(D2<=1,IF(E2<=19,1,2),IF(D2<=3,IF(E2<=5,1,IF(E2<=19,2,3)),IF(E2<=5,2,3)))),4,5,7),CHOOSE(IF(C2="EI",IF(D2<=1,IF(E2<=15,1,2),IF(D2=2,IF(E2<=4,1,IF(E2<=15,2,3)),IF(E2<=4,2,3))),IF(D2<=1,IF(E2<=19,1,2),IF(D2<=3,IF(E2<=5,1,IF(E2<=19,2,3)),IF(E2<=5,2,3)))),3,4,6))) -> 3 | H2: D01 | I2: FR01
A3: F02 | B3: Подтверждение email | C3: EI | D3: 1 | E3: 2 | F3: =CHOOSE(IF(C3="EI",IF(D3<=1,IF(E3<=15,1,2),IF(D3=2,IF(E3<=4,1,IF(E3<=15,2,3)),IF(E3<=4,2,3))),IF(D3<=1,IF(E3<=19,1,2),IF(D3<=3,IF(E3<=5,1,IF(E3<=19,2,3)),IF(E3<=5,2,3)))),"Низкая","Средняя","Высокая") -> Низкая | G3: =IF(C3="EI",CHOOSE(IF(C3="EI",IF(D3<=1,IF(E3<=15,1,2),IF(D3=2,IF(E3<=4,1,IF(E3<=15,2,3)),IF(E3<=4,2,3))),IF(D3<=1,IF(E3<=19,1,2),IF(D3<=3,IF(E3<=5,1,IF(E3<=19,2,3)),IF(E3<=5,2,3)))),3,4,6),IF(C3="EO",CHOOSE(IF(C3="EI",IF(D3<=1,IF(E3<=15,1,2),IF(D3=2,IF(E3<=4,1,IF(E3<=15,2,3)),IF(E3<=4,2,3))),IF(D3<=1,IF(E3<=19,1,2),IF(D3<=3,IF(E3<=5,1,IF(E3<=19,2,3)),IF(E3<=5,2,3)))),4,5,7),CHOOSE(IF(C3="EI",IF(D3<=1,IF(E3<=15,1,2),IF(D3=2,IF(E3<=4,1,IF(E3<=15,2,3)),IF(E3<=4,2,3))),IF(D3<=1,IF(E3<=19,1,2),IF(D3<=3,IF(E3<=5,1,IF(E3<=19,2,3)),IF(E3<=5,2,3)))),3,4,6))) -> 3 | H3: D01 | I3: FR01
A4: F03 | B4: Вход | C4: EI | D4: 1 | E4: 3 | F4: =CHOOSE(IF(C4="EI",IF(D4<=1,IF(E4<=15,1,2),IF(D4=2,IF(E4<=4,1,IF(E4<=15,2,3)),IF(E4<=4,2,3))),IF(D4<=1,IF(E4<=19,1,2),IF(D4<=3,IF(E4<=5,1,IF(E4<=19,2,3)),IF(E4<=5,2,3)))),"Низкая","Средняя","Высокая") -> Низкая | G4: =IF(C4="EI",CHOOSE(IF(C4="EI",IF(D4<=1,IF(E4<=15,1,2),IF(D4=2,IF(E4<=4,1,IF(E4<=15,2,3)),IF(E4<=4,2,3))),IF(D4<=1,IF(E4<=19,1,2),IF(D4<=3,IF(E4<=5,1,IF(E4<=19,2,3)),IF(E4<=5,2,3)))),3,4,6),IF(C4="EO",CHOOSE(IF(C4="EI",IF(D4<=1,IF(E4<=15,1,2),IF(D4=2,IF(E4<=4,1,IF(E4<=15,2,3)),IF(E4<=4,2,3))),IF(D4<=1,IF(E4<=19,1,2),IF(D4<=3,IF(E4<=5,1,IF(E4<=19,2,3)),IF(E4<=5,2,3)))),4,5,7),CHOOSE(IF(C4="EI",IF(D4<=1,IF(E4<=15,1,2),IF(D4=2,IF(E4<=4,1,IF(E4<=15,2,3)),IF(E4<=4,2,3))),IF(D4<=1,IF(E4<=19,1,2),IF(D4<=3,IF(E4<=5,1,IF(E4<=19,2,3)),IF(E4<=5,2,3)))),3,4,6))) -> 3 | H4: D01 | I4: FR02
A5: F04 | B5: Выход | C5: EI | D5: 1 | E5: 1 | F5: =CHOOSE(IF(C5="EI",IF(D5<=1,IF(E5<=15,1,2),IF(D5=2,IF(E5<=4,1,IF(E5<=15,2,3)),IF(E5<=4,2,3))),IF(D5<=1,IF(E5<=19,1,2),IF(D5<=3,IF(E5<=5,1,IF(E5<=19,2,3)),IF(E5<=5,2,3)))),"Низкая","Средняя","Высокая") -> Низкая | G5: =IF(C5="EI",CHOOSE(IF(C5="EI",IF(D5<=1,IF(E5<=15,1,2),IF(D5=2,IF(E5<=4,1,IF(E5<=15,2,3)),IF(E5<=4,2,3))),IF(D5<=1,IF(E5<=19,1,2),IF(D5<=3,IF(E5<=5,1,IF(E5<=19,2,3)),IF(E5<=5,2,3)))),3,4,6),IF(C5="EO",CHOOSE(IF(C5="EI",IF(D5<=1,IF(E5<=15,1,2),IF(D5=2,IF(E5<=4,1,IF(E5<=15,2,3)),IF(E5<=4,2,3))),IF(D5<=1,IF(E5<=19,1,2),IF(D5<=3,IF(E5<=5,1,IF(E5<=19,2,3)),IF(E5<=5,2,3)))),4,5,7),CHOOSE(IF(C5="EI",IF(D5<=1,IF(E5<=15,1,2),IF(D5=2,IF(E5<=4,1,IF(E5<=15,2,3)),IF(E5<=4,2,3))),IF(D5<=1,IF(E5<=19,1,2),IF(D5<=3,IF(E5<=5,1,IF(E5<=19,2,3)),IF(E5<=5,2,3)))),3,4,6))) -> 3 | H5: D01 | I5: FR02
A6: F05 | B6: Запрос сброса пароля | C6: EI | D6: 1 | E6: 2 | F6: =CHOOSE(IF(C6="EI",IF(D6<=1,IF(E6<=15,1,2),IF(D6=2,IF(E6<=4,1,IF(E6<=15,2,3)),IF(E6<=4,2,3))),IF(D6<=1,IF(E6<=19,1,2),IF(D6<=3,IF(E6<=5,1,IF(E6<=19,2,3)),IF(E6<=5,2,3)))),"Низкая","Средняя","Высокая") -> Низкая | G6: =IF(C6="EI",CHOOSE(IF(C6="EI",IF(D6<=1,IF(E6<=15,1,2),IF(D6=2,IF(E6<=4,1,IF(E6<=15,2,3)),IF(E6<=4,2,3))),IF(D6<=1,IF(E6<=19,1,2),IF(D6<=3,IF(E6<=5,1,IF(E6<=19,2,3)),IF(E6<=5,2,3)))),3,4,6),IF(C6="EO",CHOOSE(IF(C6="EI",IF(D6<=1,IF(E6<=15,1,2),IF(D6=2,IF(E6<=4,1,IF(E6<=15,2,3)),IF(E6<=4,2,3))),IF(D6<=1,IF(E6<=19,1,2),IF(D6<=3,IF(E6<=5,1,IF(E6<=19,2,3)),IF(E6<=5,2,3)))),4,5,7),CHOOSE(IF(C6="EI",IF(D6<=1,IF(E6<=15,1,2),IF(D6=2,IF(E6<=4,1,IF(E6<=15,2,3)),IF(E6<=4,2,3))),IF(D6<=1,IF(E6<=19,1,2),IF(D6<=3,IF(E6<=5,1,IF(E6<=19,2,3)),IF(E6<=5,2,3)))),3,4,6))) -> 3 | H6: D01 | I6: FR02
A7: F06 | B7: Смена пароля по токену | C7: EI | D7: 1 | E7: 3 | F7: =CHOOSE(IF(C7="EI",IF(D7<=1,IF(E7<=15,1,2),IF(D7=2,IF(E7<=4,1,IF(E7<=15,2,3)),IF(E7<=4,2,3))),IF(D7<=1,IF(E7<=19,1,2),IF(D7<=3,IF(E7<=5,1,IF(E7<=19,2,3)),IF(E7<=5,2,3)))),"Низкая","Средняя","Высокая") -> Низкая | G7: =IF(C7="EI",CHOOSE(IF(C7="EI",IF(D7<=1,IF(E7<=15,1,2),IF(D7=2,IF(E7<=4,1,IF(E7<=15,2,3)),IF(E7<=4,2,3))),IF(D7<=1,IF(E7<=19,1,2),IF(D7<=3,IF(E7<=5,1,IF(E7<=19,2,3)),IF(E7<=5,2,3)))),3,4,6),IF(C7="EO",CHOOSE(IF(C7="EI",IF(D7<=1,IF(E7<=15,1,2),IF(D7=2,IF(E7<=4,1,IF(E7<=15,2,3)),IF(E7<=4,2,3))),IF(D7<=1,IF(E7<=19,1,2),IF(D7<=3,IF(E7<=5,1,IF(E7<=19,2,3)),IF(E7<=5,2,3)))),4,5,7),CHOOSE(IF(C7="EI",IF(D7<=1,IF(E7<=15,1,2),IF(D7=2,IF(E7<=4,1,IF(E7<=15,2,3)),IF(E7<=4,2,3))),IF(D7<=1,IF(E7<=19,1,2),IF(D7<=3,IF(E7<=5,1,IF(E7<=19,2,3)),IF(E7<=5,2,3)))),3,4,6))) -> 3 | H7: D01 | I7: FR02
A8: F07 | B8: Изменение профиля и настроек | C8: EI | D8: 1 | E8: 10 | F8: =CHOOSE(IF(C8="EI",IF(D8<=1,IF(E8<=15,1,2),IF(D8=2,IF(E8<=4,1,IF(E8<=15,2,3)),IF(E8<=4,2,3))),IF(D8<=1,IF(E8<=19,1,2),IF(D8<=3,IF(E8<=5,1,IF(E8<=19,2,3)),IF(E8<=5,2,3)))),"Низкая","Средняя","Высокая") -> Низкая | G8: =IF(C8="EI",CHOOSE(IF(C8="EI",IF(D8<=1,IF(E8<=15,1,2),IF(D8=2,IF(E8<=4,1,IF(E8<=15,2,3)),IF(E8<=4,2,3))),IF(D8<=1,IF(E8<=19,1,2),IF(D8<=3,IF(E8<=5,1,IF(E8<=19,2,3)),IF(E8<=5,2,3)))),3,4,6),IF(C8="EO",CHOOSE(IF(C8="EI",IF(D8<=1,IF(E8<=15,1,2),IF(D8=2,IF(E8<=4,1,IF(E8<=15,2,3)),IF(E8<=4,2,3))),IF(D8<=1,IF(E8<=19,1,2),IF(D8<=3,IF(E8<=5,1,IF(E8<=19,2,3)),IF(E8<=5,2,3)))),4,5,7),CHOOSE(IF(C8="EI",IF(D8<=1,IF(E8<=15,1,2),IF(D8=2,IF(E8<=4,1,IF(E8<=15,2,3)),IF(E8<=4,2,3))),IF(D8<=1,IF(E8<=19,1,2),IF(D8<=3,IF(E8<=5,1,IF(E8<=19,2,3)),IF(E8<=5,2,3)))),3,4,6))) -> 3 | H8: D01 | I8: FR03
A9: F08 | B9: Чтение профиля | C9: EQ | D9: 1 | E9: 12 | F9: =CHOOSE(IF(C9="EI",IF(D9<=1,IF(E9<=15,1,2),IF(D9=2,IF(E9<=4,1,IF(E9<=15,2,3)),IF(E9<=4,2,3))),IF(D9<=1,IF(E9<=19,1,2),IF(D9<=3,IF(E9<=5,1,IF(E9<=19,2,3)),IF(E9<=5,2,3)))),"Низкая","Средняя","Высокая") -> Низкая | G9: =IF(C9="EI",CHOOSE(IF(C9="EI",IF(D9<=1,IF(E9<=15,1,2),IF(D9=2,IF(E9<=4,1,IF(E9<=15,2,3)),IF(E9<=4,2,3))),IF(D9<=1,IF(E9<=19,1,2),IF(D9<=3,IF(E9<=5,1,IF(E9<=19,2,3)),IF(E9<=5,2,3)))),3,4,6),IF(C9="EO",CHOOSE(IF(C9="EI",IF(D9<=1,IF(E9<=15,1,2),IF(D9=2,IF(E9<=4,1,IF(E9<=15,2,3)),IF(E9<=4,2,3))),IF(D9<=1,IF(E9<=19,1,2),IF(D9<=3,IF(E9<=5,1,IF(E9<=19,2,3)),IF(E9<=5,2,3)))),4,5,7),CHOOSE(IF(C9="EI",IF(D9<=1,IF(E9<=15,1,2),IF(D9=2,IF(E9<=4,1,IF(E9<=15,2,3)),IF(E9<=4,2,3))),IF(D9<=1,IF(E9<=19,1,2),IF(D9<=3,IF(E9<=5,1,IF(E9<=19,2,3)),IF(E9<=5,2,3)))),3,4,6))) -> 3 | H9: D01 | I9: FR03
A10: F09 | B10: Поиск и фильтрация каталога | C10: EQ | D10: 2 | E10: 12 | F10: =CHOOSE(IF(C10="EI",IF(D10<=1,IF(E10<=15,1,2),IF(D10=2,IF(E10<=4,1,IF(E10<=15,2,3)),IF(E10<=4,2,3))),IF(D10<=1,IF(E10<=19,1,2),IF(D10<=3,IF(E10<=5,1,IF(E10<=19,2,3)),IF(E10<=5,2,3)))),"Низкая","Средняя","Высокая") -> Средняя | G10: =IF(C10="EI",CHOOSE(IF(C10="EI",IF(D10<=1,IF(E10<=15,1,2),IF(D10=2,IF(E10<=4,1,IF(E10<=15,2,3)),IF(E10<=4,2,3))),IF(D10<=1,IF(E10<=19,1,2),IF(D10<=3,IF(E10<=5,1,IF(E10<=19,2,3)),IF(E10<=5,2,3)))),3,4,6),IF(C10="EO",CHOOSE(IF(C10="EI",IF(D10<=1,IF(E10<=15,1,2),IF(D10=2,IF(E10<=4,1,IF(E10<=15,2,3)),IF(E10<=4,2,3))),IF(D10<=1,IF(E10<=19,1,2),IF(D10<=3,IF(E10<=5,1,IF(E10<=19,2,3)),IF(E10<=5,2,3)))),4,5,7),CHOOSE(IF(C10="EI",IF(D10<=1,IF(E10<=15,1,2),IF(D10=2,IF(E10<=4,1,IF(E10<=15,2,3)),IF(E10<=4,2,3))),IF(D10<=1,IF(E10<=19,1,2),IF(D10<=3,IF(E10<=5,1,IF(E10<=19,2,3)),IF(E10<=5,2,3)))),3,4,6))) -> 4 | H10: D02, D13 | I10: FR04
A11: F10 | B11: Просмотр карточки курса | C11: EQ | D11: 4 | E11: 22 | F11: =CHOOSE(IF(C11="EI",IF(D11<=1,IF(E11<=15,1,2),IF(D11=2,IF(E11<=4,1,IF(E11<=15,2,3)),IF(E11<=4,2,3))),IF(D11<=1,IF(E11<=19,1,2),IF(D11<=3,IF(E11<=5,1,IF(E11<=19,2,3)),IF(E11<=5,2,3)))),"Низкая","Средняя","Высокая") -> Высокая | G11: =IF(C11="EI",CHOOSE(IF(C11="EI",IF(D11<=1,IF(E11<=15,1,2),IF(D11=2,IF(E11<=4,1,IF(E11<=15,2,3)),IF(E11<=4,2,3))),IF(D11<=1,IF(E11<=19,1,2),IF(D11<=3,IF(E11<=5,1,IF(E11<=19,2,3)),IF(E11<=5,2,3)))),3,4,6),IF(C11="EO",CHOOSE(IF(C11="EI",IF(D11<=1,IF(E11<=15,1,2),IF(D11=2,IF(E11<=4,1,IF(E11<=15,2,3)),IF(E11<=4,2,3))),IF(D11<=1,IF(E11<=19,1,2),IF(D11<=3,IF(E11<=5,1,IF(E11<=19,2,3)),IF(E11<=5,2,3)))),4,5,7),CHOOSE(IF(C11="EI",IF(D11<=1,IF(E11<=15,1,2),IF(D11=2,IF(E11<=4,1,IF(E11<=15,2,3)),IF(E11<=4,2,3))),IF(D11<=1,IF(E11<=19,1,2),IF(D11<=3,IF(E11<=5,1,IF(E11<=19,2,3)),IF(E11<=5,2,3)))),3,4,6))) -> 6 | H11: D01, D02, D03, D13 | I11: FR05
A12: F11 | B12: Запись на бесплатный курс | C12: EI | D12: 3 | E12: 3 | F12: =CHOOSE(IF(C12="EI",IF(D12<=1,IF(E12<=15,1,2),IF(D12=2,IF(E12<=4,1,IF(E12<=15,2,3)),IF(E12<=4,2,3))),IF(D12<=1,IF(E12<=19,1,2),IF(D12<=3,IF(E12<=5,1,IF(E12<=19,2,3)),IF(E12<=5,2,3)))),"Низкая","Средняя","Высокая") -> Средняя | G12: =IF(C12="EI",CHOOSE(IF(C12="EI",IF(D12<=1,IF(E12<=15,1,2),IF(D12=2,IF(E12<=4,1,IF(E12<=15,2,3)),IF(E12<=4,2,3))),IF(D12<=1,IF(E12<=19,1,2),IF(D12<=3,IF(E12<=5,1,IF(E12<=19,2,3)),IF(E12<=5,2,3)))),3,4,6),IF(C12="EO",CHOOSE(IF(C12="EI",IF(D12<=1,IF(E12<=15,1,2),IF(D12=2,IF(E12<=4,1,IF(E12<=15,2,3)),IF(E12<=4,2,3))),IF(D12<=1,IF(E12<=19,1,2),IF(D12<=3,IF(E12<=5,1,IF(E12<=19,2,3)),IF(E12<=5,2,3)))),4,5,7),CHOOSE(IF(C12="EI",IF(D12<=1,IF(E12<=15,1,2),IF(D12=2,IF(E12<=4,1,IF(E12<=15,2,3)),IF(E12<=4,2,3))),IF(D12<=1,IF(E12<=19,1,2),IF(D12<=3,IF(E12<=5,1,IF(E12<=19,2,3)),IF(E12<=5,2,3)))),3,4,6))) -> 4 | H12: D01, D02, D05 | I12: FR06
A13: F12 | B13: Список моих курсов | C13: EQ | D13: 2 | E13: 10 | F13: =CHOOSE(IF(C13="EI",IF(D13<=1,IF(E13<=15,1,2),IF(D13=2,IF(E13<=4,1,IF(E13<=15,2,3)),IF(E13<=4,2,3))),IF(D13<=1,IF(E13<=19,1,2),IF(D13<=3,IF(E13<=5,1,IF(E13<=19,2,3)),IF(E13<=5,2,3)))),"Низкая","Средняя","Высокая") -> Средняя | G13: =IF(C13="EI",CHOOSE(IF(C13="EI",IF(D13<=1,IF(E13<=15,1,2),IF(D13=2,IF(E13<=4,1,IF(E13<=15,2,3)),IF(E13<=4,2,3))),IF(D13<=1,IF(E13<=19,1,2),IF(D13<=3,IF(E13<=5,1,IF(E13<=19,2,3)),IF(E13<=5,2,3)))),3,4,6),IF(C13="EO",CHOOSE(IF(C13="EI",IF(D13<=1,IF(E13<=15,1,2),IF(D13=2,IF(E13<=4,1,IF(E13<=15,2,3)),IF(E13<=4,2,3))),IF(D13<=1,IF(E13<=19,1,2),IF(D13<=3,IF(E13<=5,1,IF(E13<=19,2,3)),IF(E13<=5,2,3)))),4,5,7),CHOOSE(IF(C13="EI",IF(D13<=1,IF(E13<=15,1,2),IF(D13=2,IF(E13<=4,1,IF(E13<=15,2,3)),IF(E13<=4,2,3))),IF(D13<=1,IF(E13<=19,1,2),IF(D13<=3,IF(E13<=5,1,IF(E13<=19,2,3)),IF(E13<=5,2,3)))),3,4,6))) -> 4 | H13: D02, D05 | I13: FR06
... A61: F60 | B61: Архивация категории | C61: EI | D61: 2 | E61: 2 | F61: =CHOOSE(IF(C61="EI",IF(D61<=1,IF(E61<=15,1,2),IF(D61=2,IF(E61<=4,1,IF(E61<=15,2,3)),IF(E61<=4,2,3))),IF(D61<=1,IF(E61<=19,1,2),IF(D61<=3,IF(E61<=5,1,IF(E61<=19,2,3)),IF(E61<=5,2,3)))),"Низкая","Средняя","Высокая") -> Низкая | G61: =IF(C61="EI",CHOOSE(IF(C61="EI",IF(D61<=1,IF(E61<=15,1,2),IF(D61=2,IF(E61<=4,1,IF(E61<=15,2,3)),IF(E61<=4,2,3))),IF(D61<=1,IF(E61<=19,1,2),IF(D61<=3,IF(E61<=5,1,IF(E61<=19,2,3)),IF(E61<=5,2,3)))),3,4,6),IF(C61="EO",CHOOSE(IF(C61="EI",IF(D61<=1,IF(E61<=15,1,2),IF(D61=2,IF(E61<=4,1,IF(E61<=15,2,3)),IF(E61<=4,2,3))),IF(D61<=1,IF(E61<=19,1,2),IF(D61<=3,IF(E61<=5,1,IF(E61<=19,2,3)),IF(E61<=5,2,3)))),4,5,7),CHOOSE(IF(C61="EI",IF(D61<=1,IF(E61<=15,1,2),IF(D61=2,IF(E61<=4,1,IF(E61<=15,2,3)),IF(E61<=4,2,3))),IF(D61<=1,IF(E61<=19,1,2),IF(D61<=3,IF(E61<=5,1,IF(E61<=19,2,3)),IF(E61<=5,2,3)))),3,4,6))) -> 3 | H61: D02, D13 | I61: FR24

Sheet VAF
A1: Характеристика | B1: DI (0–5)
A2: Обмен данными | B2: 4
A3: Распределённая обработка | B3: 3
A4: Производительность | B4: 3
A5: Ограничения конфигурации | B5: 1
A6: Частота транзакций | B6: 3
A7: Интерактивный ввод | B7: 5
A8: Эффективность пользователя | B8: 4
A9: Интерактивное обновление | B9: 4
A10: Сложность обработки | B10: 3
A11: Повторное использование | B11: 2
A12: Простота установки | B12: 2
A13: Удобство эксплуатации | B13: 3
... A15: Удобство изменений | B15: 4

Sheet COCOMO факторы
A1: Фактор | B1: Значение | C1: Уровень | D1: Обоснование
A2: PREC | B2: 3.72 | C2: Nominal | D2: Типовая LMS, но нет опыта именно этого продукта.
A3: FLEX | B3: 3.04 | C3: Nominal | D3: Функциональные границы согласованы, интерфейсы допускают изменения.
A4: RESL | B4: 4.24 | C4: Nominal | D4: Архитектура предварительная, интеграционные риски остаются.
A5: TEAM | B5: 3.29 | C5: Nominal | D5: Предполагается обычная сработанность проектной команды.
A6: PMAT | B6: 4.68 | C6: Nominal | D6: Учебное допущение об обычной зрелости процесса.
A7: PERS | B7: 1 | C7: Nominal | D7: Нет подтверждённых данных о производительности команды.
A8: RCPX | B8: 1.33 | C8: High | D8: Платежи, оценивание и асинхронная проверка повышают сложность.
A9: PDIF | B9: 1 | C9: Nominal | D9: Нет жёстких аппаратных ограничений.
A10: PREX | B10: 1 | C10: Nominal | D10: Средний опыт стека и предметной области — допущение.
A11: FCIL | B11: 0.87 | C11: High | D11: Готовые CI, средства тестирования и совместной работы.
A12: RUSE | B12: 1 | C12: Nominal | D12: Повторное использование в рамках проекта.
A13: SCED | B13: 1 | C13: Nominal | D13: Срок искусственно не сжимается.

Sheet UCP прецеденты
A1: ID | B1: Прецедент | C1: Акторы | D1: FR | E1: Транзакции сценария | F1: Количество | G1: Вес
A2: UC01 | B2: Регистрация | C2: Гость | D2: FR01 | E2: 1. Ввод регистрационных данных; 2. Проверка и создание аккаунта; 3. Подтверждение адреса; 4. Активация аккаунта | F2: 4 | G2: =IF(F2<=3,5,IF(F2<=7,10,15)) -> 10
A3: UC02 | B3: Вход и завершение сессии | C3: Гость | D3: FR02 | E3: 1. Передача учётных данных; 2. Проверка и создание сессии; 3. Завершение сессии | F3: 3 | G3: =IF(F3<=3,5,IF(F3<=7,10,15)) -> 5
A4: UC03 | B4: Восстановление доступа | C4: Гость | D4: FR02 | E4: 1. Запрос восстановления; 2. Выдача ссылки; 3. Передача нового пароля; 4. Проверка токена и смена пароля | F4: 4 | G4: =IF(F4<=3,5,IF(F4<=7,10,15)) -> 10
A5: UC04 | B5: Настройка профиля | C5: Учащийся | D5: FR03 | E5: 1. Получение профиля; 2. Передача изменений; 3. Валидация и сохранение | F5: 3 | G5: =IF(F5<=3,5,IF(F5<=7,10,15)) -> 5
A6: UC05 | B6: Поиск курса | C6: Гость | D6: FR04 | E6: 1. Задание запроса и фильтров; 2. Получение подходящих курсов; 3. Выбор страницы результатов | F6: 3 | G6: =IF(F6<=3,5,IF(F6<=7,10,15)) -> 5
A7: UC06 | B7: Изучение карточки курса | C7: Гость | D7: FR05 | E7: 1. Запрос карточки; 2. Получение описания и программы; 3. Получение условий доступа | F7: 3 | G7: =IF(F7<=3,5,IF(F7<=7,10,15)) -> 5
A8: UC07 | B8: Запись и выбор своего курса | C8: Учащийся | D8: FR06 | E8: 1. Запрос записи; 2. Проверка доступности; 3. Создание доступа; 4. Получение списка своих курсов | F8: 4 | G8: =IF(F8<=3,5,IF(F8<=7,10,15)) -> 10
A9: UC08 | B9: Изучение материалов | C9: Учащийся | D9: FR07 | E9: 1. Выбор урока; 2. Проверка доступа; 3. Получение шага; 4. Сохранение позиции | F9: 4 | G9: =IF(F9<=3,5,IF(F9<=7,10,15)) -> 10
A10: UC09 | B10: Решение тестовой задачи | C10: Учащийся | D10: FR08 | E10: 1. Получение условия; 2. Передача ответа; 3. Проверка ограничений; 4. Проверка ответа; 5. Сохранение результата; 6. Получение обратной связи | F10: 6 | G10: =IF(F10<=3,5,IF(F10<=7,10,15)) -> 10
A11: UC10 | B11: Решение задачи на код | C11: Учащийся, Grader API | D11: FR09 | E11: 1. Получение условия; 2. Передача кода; 3. Валидация языка и доступа; 4. Постановка в очередь; 5. Передача grader; 6. Получение результата; 7. Сохранение попытки; 8. Выдача результата учащемуся | F11: 8 | G11: =IF(F11<=3,5,IF(F11<=7,10,15)) -> 15
A12: UC11 | B12: Просмотр прогресса | C12: Учащийся | D12: FR10 | E12: 1. Запрос прогресса; 2. Расчёт баллов и доли прохождения; 3. Получение сводки | F12: 3 | G12: =IF(F12<=3,5,IF(F12<=7,10,15)) -> 5
A13: UC12 | B13: Получение и проверка сертификата | C13: Учащийся, Гость | D13: FR11 | E13: 1. Запрос сертификата; 2. Проверка порога; 3. Формирование документа; 4. Получение ссылки; 5. Проверка подлинности по ссылке | F13: 5 | G13: =IF(F13<=3,5,IF(F13<=7,10,15)) -> 10
... A26: UC25 | B26: Управление категориями | C26: Модератор | D26: FR24 | E26: 1. Получение справочника; 2. Передача новой категории; 3. Проверка и сохранение; 4. Изменение категории; 5. Архивация с проверкой связей | F26: 5 | G26: =IF(F26<=3,5,IF(F26<=7,10,15)) -> 10

Sheet UCP акторы
A1: Актор | B1: Вес | C1: Интерфейс
A2: Гость | B2: 3 | C2: Человек, графический интерфейс
A3: Учащийся | B3: 3 | C3: Человек, графический интерфейс
A4: Преподаватель | B4: 3 | C4: Человек, графический интерфейс
A5: Модератор | B5: 3 | C5: Человек, графический интерфейс; включает администратора
A6: Платёжный API | B6: 1 | C6: Внешняя система, программный API
A7: Grader API | B7: 1 | C7: Внешняя система, программный API
A8: Email API | B8: 1 | C8: Внешняя система, программный API
A9: Media API | B9: 1 | C9: Внешнее объектное хранилище, программный API

Sheet UCP факторы
A1: ID | B1: Фактор | C1: Вес | D1: Оценка | E1: Произведение | F1: Обоснование
A2: T1 | B2: Распределённость | C2: 2 | D2: 3 | E2: =C2*D2 -> 6 | F2: Веб-приложение и внешние сервисы.
A3: T2 | B3: Производительность | C3: 1 | D3: 3 | E3: =C3*D3 -> 3 | F3: Поиск и поток ответов.
A4: T3 | B4: Эффективность пользователя | C4: 1 | D4: 4 | E4: =C4*D4 -> 4 | F4: Длительные учебные сессии.
A5: T4 | B5: Сложная обработка | C5: 1 | D5: 3 | E5: =C5*D5 -> 3 | F5: Прогресс, платежи и grader.
A6: T5 | B6: Повторное использование | C6: 1 | D6: 2 | E6: =C6*D6 -> 2 | F6: Компоненты внутри системы.
A7: T6 | B7: Простота установки | C7: 0.5 | D7: 2 | E7: =C7*D7 -> 1 | F7: Серверный выпуск через CI.
A8: T7 | B8: Простота использования | C8: 0.5 | D8: 4 | E8: =C8*D8 -> 2 | F8: Учащиеся без подготовки.
A9: T8 | B9: Переносимость | C9: 2 | D9: 2 | E9: =C9*D9 -> 4 | F9: Поддержка основных браузеров.
A10: T9 | B10: Простота изменений | C10: 1 | D10: 3 | E10: =C10*D10 -> 3 | F10: Развитие типов заданий.
A11: T10 | B11: Параллельность | C11: 1 | D11: 4 | E11: =C11*D11 -> 4 | F11: Одновременные ответы и callback.
A12: T11 | B12: Безопасность | C12: 1 | D12: 4 | E12: =C12*D12 -> 4 | F12: Доступ, персональные данные, оплата.
A13: T12 | B13: Доступ третьих сторон | C13: 1 | D13: 2 | E13: =C13*D13 -> 2 | F13: Ограниченные callback интеграций.
... A22: E8 | B22: Сложность языка | C22: -1 | D22: 2 | E22: =C22*D22 -> -2 | F22: Знакомый стек, сложные интеграции.

Sheet Итоги
A1: Показатель | B1: Значение
A2: Наивная трудоёмкость, чел·ч | B2: =Работы!G34 -> 2304
A3: PERT трудоёмкость, чел·ч | B3: =Работы!I34 -> 2428
A4: PERT σ, чел·ч | B4: =Работы!J34 -> 78.145164
A5: 95% нижняя (приближение) | B5: =B3-1.96*B4 -> 2274.8355
A6: 95% верхняя (приближение) | B6: =B3+1.96*B4 -> 2581.1645
A7: CPM, рабочие часы | B7: =MAX(CPM!E2:E33) -> 1234.6667
A8: ILF | B8: =SUM('FP данные'!G2:G15) -> 107
A9: EIF | B9: 0
A10: Транзакции | B10: =SUM('FP транзакции'!G2:G61) -> 254
A11: UFP | B11: =SUM(B8:B10) -> 361
A12: VAF | B12: =0.65+0.01*SUM(VAF!B2:B15) -> 1.07
A13: AFP | B13: =B11*B12 -> 386.27
A14: SLOC / UFP | B14: 47
A15: KSLOC | B15: =B11*B14/1000 -> 16.967
A16: ΣSF | B16: =SUM('COCOMO факторы'!B2:B6) -> 18.97
A17: E | B17: =0.91+0.01*B16 -> 1.0997
A18: EAF | B18: =PRODUCT('COCOMO факторы'!B7:B13) -> 1.1571
A19: COCOMO PM | B19: =2.94*B15^B17*B18 -> 76.544662
A20: COCOMO чел·ч | B20: =B19*152 -> 11634.789
A21: F | B21: =0.28+0.2*(B17-0.91) -> 0.31794
A22: TDEV, месяцев | B22: =3.67*B19^B21 -> 14.575987
A23: Средняя команда COCOMO | B23: =B19/B22 -> 5.2514222
A24: UUCW | B24: =SUM('UCP прецеденты'!G2:G26) -> 240
A25: UAW | B25: =SUM('UCP акторы'!B2:B9) -> 16
A26: TF | B26: =SUM('UCP факторы'!E2:E14) -> 40
A27: TCF | B27: =0.6+0.01*B26 -> 1
A28: EF | B28: =SUM('UCP факторы'!E15:E22) -> 17
A29: ECF | B29: =1.4-0.03*B28 -> 0.89
A30: UCP | B30: =(B24+B25)*B27*B29 -> 227.84
A31: PF — сценарий, не калибровка | B31: 20
A32: UCP трудоёмкость, сценарий | B32: =B30*B31 -> 4556.8

Sheet PF чувствительность
A1: PF, чел·ч/UCP | B1: Трудоёмкость, чел·ч | C1: Статус
A2: 10 | B2: =Итоги!B30*A2 -> 2278.4 | C2: Сценарий; данных завершённого проекта нет
A3: 20 | B3: =Итоги!B30*A3 -> 4556.8 | C3: Сценарий; данных завершённого проекта нет
A4: 30 | B4: =Итоги!B30*A4 -> 6835.2 | C4: Сценарий; данных завершённого проекта нет

Sheet Источники
A1: ID | B1: Название | C1: URL | D1: Что подтверждает
A2: S1 | B2: Stepik: каталог курсов | C2: https://stepik.org/catalog | D2: Веб-каталог; динамическая страница. Подробности функций проверены по справочному центру.
A3: S2 | B3: С чего начать | C3: https://help.stepik.org/article/54712 | D3: Каталог, поиск и начало обучения.
A4: S3 | B4: Структура курса | C4: https://help.stepik.org/article/54734 | D4: Модули, уроки, шаги и прогресс.
A5: S4 | B5: Как создать урок и курс | C5: https://help.stepik.org/article/54788 | D5: Редактор и публикация учебного контента.
A6: S5 | B6: Виды практических задач | C6: https://help.stepik.org/article/54741 | D6: Автоматическая проверка, программирование, ручное рецензирование.
A7: S6 | B7: Как оплатить курс | C7: https://help.stepik.org/article/54772 | D7: Покупка, промокоды, зачисление после оплаты.
A8: S7 | B8: Настройка сертификатов в курсах | C8: https://help.stepik.org/article/54825 | D8: Порог баллов, обычный сертификат и сертификат с отличием.
A9: S8 | B9: Поддержка курса (комментарии, нотификации) | C9: https://help.stepik.org/article/54810 | D9: Комментарии, новости и уведомления.
A10: S9 | B10: Статистика по курсу | C10: https://help.stepik.org/article/54814 | D10: Отчётность по результатам обучения.
A11: S10 | B11: Категории курса | C11: https://help.stepik.org/article/60913 | D11: Категоризация курсов.
A12: S11 | B12: Правила сообщества Stepik | C12: https://help.stepik.org/article/54715 | D12: Модерация и ограничения общения.
... A16: M4 | B16: Anda et al.: Estimating Software Development Effort Based on Use Cases — Experiences from Industry (2001) | C16: https://web-backend.simula.no/sites/default/files/publications/SE.5.Anda.2001.a.pdf | D16: Исследование применения UCP; ориентир 20 чел·ч/UCP не заменяет локальную калибровку.
